huaweicloudsdkiamaccessanalyzer/__init__.py
huaweicloudsdkiamaccessanalyzer/v1/__init__.py
huaweicloudsdkiamaccessanalyzer/v1/iamaccessanalyzer_async_client.py
huaweicloudsdkiamaccessanalyzer/v1/iamaccessanalyzer_client.py
huaweicloudsdkiamaccessanalyzer/v1/model/__init__.py
huaweicloudsdkiamaccessanalyzer/v1/model/access_preview.py
huaweicloudsdkiamaccessanalyzer/v1/model/access_preview_id.py
huaweicloudsdkiamaccessanalyzer/v1/model/access_preview_status.py
huaweicloudsdkiamaccessanalyzer/v1/model/access_preview_summary.py
huaweicloudsdkiamaccessanalyzer/v1/model/analyzer_configuration.py
huaweicloudsdkiamaccessanalyzer/v1/model/analyzer_configuration_unused_access.py
huaweicloudsdkiamaccessanalyzer/v1/model/analyzer_id.py
huaweicloudsdkiamaccessanalyzer/v1/model/analyzer_name.py
huaweicloudsdkiamaccessanalyzer/v1/model/analyzer_summary.py
huaweicloudsdkiamaccessanalyzer/v1/model/analyzer_type.py
huaweicloudsdkiamaccessanalyzer/v1/model/analyzer_urn.py
huaweicloudsdkiamaccessanalyzer/v1/model/apply_archive_rule_request.py
huaweicloudsdkiamaccessanalyzer/v1/model/apply_archive_rule_response.py
huaweicloudsdkiamaccessanalyzer/v1/model/archive_rule_id.py
huaweicloudsdkiamaccessanalyzer/v1/model/archive_rule_name.py
huaweicloudsdkiamaccessanalyzer/v1/model/archive_rule_summary.py
huaweicloudsdkiamaccessanalyzer/v1/model/archive_rule_urn.py
huaweicloudsdkiamaccessanalyzer/v1/model/check_no_new_access_reason.py
huaweicloudsdkiamaccessanalyzer/v1/model/check_no_new_access_req_body.py
huaweicloudsdkiamaccessanalyzer/v1/model/check_no_new_access_request.py
huaweicloudsdkiamaccessanalyzer/v1/model/check_no_new_access_response.py
huaweicloudsdkiamaccessanalyzer/v1/model/configuration.py
huaweicloudsdkiamaccessanalyzer/v1/model/create_access_preview_req_body.py
huaweicloudsdkiamaccessanalyzer/v1/model/create_access_preview_request.py
huaweicloudsdkiamaccessanalyzer/v1/model/create_access_preview_response.py
huaweicloudsdkiamaccessanalyzer/v1/model/create_analyzer_req_body.py
huaweicloudsdkiamaccessanalyzer-3.1.184.dist-info/METADATA
huaweicloudsdkiamaccessanalyzer-3.1.184.dist-info/WHEEL
huaweicloudsdkiamaccessanalyzer-3.1.184.dist-info/licenses/LICENSE
huaweicloudsdkiamaccessanalyzer-3.1.184.dist-info/RECORD
